package org.tsers.junitquest;

import java.util.HashMap;

public class OpcodeHelper {

    public static String getName(int opcode) {
        return values.get(opcode);
    }

    static HashMap<Integer, String> values = new HashMap<Integer, String>() {
        {
            put(-2, "BEGINMETHOD");
            put(-1, "LABEL");
            put(0, "NOP");
            put(1, "ACONST_NULL");
            put(2, "ICONST_M1");
            put(3, "ICONST_0");
            put(4, "ICONST_1");
            put(5, "ICONST_2");
            put(6, "ICONST_3");
            put(7, "ICONST_4");
            put(8, "ICONST_5");
            put(9, "LCONST_0");
            put(10, "LCONST_1");
            put(11, "FCONST_0");
            put(12, "FCONST_1");
            put(13, "FCONST_2");
            put(14, "DCONST_0");
            put(15, "DCONST_1");
            put(16, "BIPUSH");
            put(17, "SIPUSH");
            put(18, "LDC");
            put(21, "ILOAD");
            put(22, "LLOAD");
            put(23, "FLOAD");
            put(24, "DLOAD");
            put(25, "ALOAD");
            put(46, "IALOAD");
            put(47, "LALOAD");
            put(48, "FALOAD");
            put(49, "DALOAD");
            put(50, "AALOAD");
            put(51, "BALOAD");
            put(52, "CALOAD");
            put(53, "SALOAD");
            put(54, "ISTORE");
            put(55, "LSTORE");
            put(56, "FSTORE");
            put(57, "DSTORE");
            put(58, "ASTORE");
            put(79, "IASTORE");
            put(80, "LASTORE");
            put(81, "FASTORE");
            put(82, "DASTORE");
            put(83, "AASTORE");
            put(84, "BASTORE");
            put(85, "CASTORE");
            put(86, "SASTORE");
            put(87, "POP");
            put(88, "POP2");
            put(89, "DUP");
            put(90, "DUP_X1");
            put(91, "DUP_X2");
            put(92, "DUP2");
            put(93, "DUP2_X1");
            put(94, "DUP2_X2");
            put(95, "SWAP");
            put(96, "IADD");
            put(97, "LADD");
            put(98, "FADD");
            put(99, "DADD");
            put(100, "ISUB");
            put(101, "LSUB");
            put(102, "FSUB");
            put(103, "DSUB");
            put(104, "IMUL");
            put(105, "LMUL");
            put(106, "FMUL");
            put(107, "DMUL");
            put(108, "IDIV");
            put(109, "LDIV");
            put(110, "FDIV");
            put(111, "DDIV");
            put(112, "IREM");
            put(113, "LREM");
            put(114, "FREM");
            put(115, "DREM");
            put(116, "INEG");
            put(117, "LNEG");
            put(118, "FNEG");
            put(119, "DNEG");
            put(120, "ISHL");
            put(121, "LSHL");
            put(122, "ISHR");
            put(123, "LSHR");
            put(124, "IUSHR");
            put(125, "LUSHR");
            put(126, "IAND");
            put(127, "LAND");
            put(128, "IOR");
            put(129, "LOR");
            put(130, "IXOR");
            put(131, "LXOR");
            put(132, "IINC");
            put(133, "I2L");
            put(134, "I2F");
            put(135, "I2D");
            put(136, "L2I");
            put(137, "L2F");
            put(138, "L2D");
            put(139, "F2I");
            put(140, "F2L");
            put(141, "F2D");
            put(142, "D2I");
            put(143, "D2L");
            put(144, "D2F");
            put(145, "I2B");
            put(146, "I2C");
            put(147, "I2S");
            put(148, "LCMP");
            put(149, "FCMPL");
            put(150, "FCMPG");
            put(151, "DCMPL");
            put(152, "DCMPG");
            put(153, "IFEQ");
            put(154, "IFNE");
            put(155, "IFLT");
            put(156, "IFGE");
            put(157, "IFGT");
            put(158, "IFLE");
            put(159, "IF_ICMPEQ");
            put(160, "IF_ICMPNE");
            put(161, "IF_ICMPLT");
            put(162, "IF_ICMPGE");
            put(163, "IF_ICMPGT");
            put(164, "IF_ICMPLE");
            put(165, "IF_ACMPEQ");
            put(166, "IF_ACMPNE");
            put(167, "GOTO");
            put(168, "JSR");
            put(169, "RET");
            put(170, "TABLESWITCH");
            put(171, "LOOKUPSWITCH");
            put(172, "IRETURN");
            put(173, "LRETURN");
            put(174, "FRETURN");
            put(175, "DRETURN");
            put(176, "ARETURN");
            put(177, "RETURN");
            put(178, "GETSTATIC");
            put(179, "PUTSTATIC");
            put(180, "GETFIELD");
            put(181, "PUTFIELD");
            put(182, "INVOKEVIRTUAL");
            put(183, "INVOKESPECIAL");
            put(184, "INVOKESTATIC");
            put(185, "INVOKEINTERFACE");
            put(186, "INVOKEDYNAMIC");
            put(187, "NEW");
            put(188, "NEWARRAY");
            put(189, "ANEWARRAY");
            put(190, "ARRAYLENGTH");
            put(191, "ATHROW");
            put(192, "CHECKCAST");
            put(193, "INSTANCEOF");
            put(194, "MONITORENTER");
            put(195, "MONITOREXIT");
            put(197, "MULTIANEWARRAY");
            put(198, "IFNULL");
            put(199, "IFNONNULL");
        }
    };
}
